{
  "metadata": {
    "title": "泣き顔絵文字のコピー＆ペースト - 無料オンライン | Toolaze",
    "description": "泣き顔の絵文字や泣いている顔の絵文字をオンラインで無料でコピー＆ペースト。嬉し泣き、泣き顔など。ワンクリックでコピー、登録不要。iPhone、Android、Discord、Instagramに対応。"
  },
  "sectionsOrder": [
    "howToUse",
    "intro",
    "performanceMetrics",
    "comparison",
    "scenes",
    "rating",
    "faq"
  ],
  "hero": {
    "h1": "泣き顔絵文字のコピー＆ペースト",
    "desc": "泣き顔の絵文字や泣いている顔の絵文字をオンラインで無料でコピー＆ペースト。嬉し泣きや悲しい顔などを見つけましょう。ワンクリックでコピーでき、あらゆるデバイスで動作します。"
  },
  "intro": {
    "title": "なぜオンラインで泣き顔絵文字をコピー＆ペーストするのか？",
    "content": [
      {
        "title": "泣き顔絵文字とは？",
        "text": "泣き顔の絵文字（😢）や大泣きの絵文字（😭）は、メッセージやSNSで悲しみ、失望、または「泣いている」反応を表現するために最もよく使われる絵文字の一つです。多くの人がテキスト、コメント、投稿で使用するために泣き顔絵文字のコピー＆ペーストを検索します。Toolazeを使えば、泣き顔、嬉し泣き、関連する顔の絵文字を即座にコピー＆ペーストできます。アプリのインストールや登録は不要です。最近使用したリストはローカルに保存されるため、検索せずに再度コピー＆ペーストできます。iPhone、Android、Discord、Instagram、TikTokで動作します。"
      },
      {
        "title": "あらゆるデバイスで泣き顔絵文字をコピー＆ペースト",
        "text": "iPhone用の泣き顔絵文字のコピー＆ペーストが必要な場合でも、Android用でも、Toolazeはブラウザで動作します。ページを開き、目的の泣き顔や嬉し泣きの絵文字をクリックして、好きな場所に貼り付けるだけです。ミーム用に嬉し泣きをコピーしたり、メッセージで標準の泣き顔を使ったりできます。すべての絵文字は標準のUnicodeであるため、すべてのプラットフォームで正しく表示されます。他のカテゴリについては、フル機能の <a href=\"/ja/emoji-copy-and-paste\" class=\"text-indigo-600 hover:text-purple-600 font-semibold underline decoration-2 underline-offset-2\">絵文字コピー＆ペースト</a> ツールをお試しください。"
      }
    ]
  },
  "specs": {
    "engine": "ブラウザベースの絵文字ピッカー - クライアントサイド",
    "limit": "無制限の絵文字 - すべての標準Unicodeカテゴリ",
    "logic": "検索 + カテゴリ閲覧 + 最近の使用",
    "privacy": "100% クライアントサイド（最近の履歴のみローカルストレージに保存）"
  },
  "performanceMetrics": {
    "title": "技術仕様",
    "metrics": [
      {
        "label": "カテゴリ",
        "value": "スマイリーと人々（泣き顔、悲しい顔、嬉し泣き）"
      },
      {
        "label": "検索",
        "value": "キーワード検索（例：泣く、悲しい、涙）"
      },
      {
        "label": "コピー",
        "value": "クリップボードへのワンクリックコピー"
      },
      {
        "label": "プラットフォーム対応",
        "value": "iPhone, Android, Discord, Instagram, TikTok, iMessage, WhatsApp"
      },
      {
        "label": "プライバシー",
        "value": "サーバーへのアップロードなし。最近のリストはローカルのみに保存"
      }
    ]
  },
  "howToUse": {
    "title": "泣き顔絵文字のコピー＆ペースト方法",
    "steps": [
      {
        "title": "絵文字ピッカーを開く",
        "desc": "Toolazeの絵文字コピー＆ペーストにアクセスし、検索または「スマイリーと人々」カテゴリから泣き顔絵文字を探します。"
      },
      {
        "title": "絵文字を選択",
        "desc": "コピー＆ペーストしたい泣き顔、大泣き、または嬉し泣きの絵文字をクリックします。"
      },
      {
        "title": "どこにでも貼り付け",
        "desc": "Ctrl+V（Macの場合はCmd+V）でメッセージ、コメント、またはSNSの投稿に貼り付けます。"
      }
    ]
  },
  "comparison": {
    "title": "なぜToolazeを選ぶのか？",
    "toolaze": "Toolaze 💎",
    "others": "他のツール",
    "vs": "VS",
    "smartChoice": "賢い選択",
    "otherTools": "他のツール",
    "toolazeFeatures": "無料、登録不要、泣く/悲しい/涙で検索、ワンクリックコピー、最近の使用履歴、ブラウザで動作、iPhoneおよびAndroid対応",
    "othersFeatures": "登録が必要、検索が限定的、広告やペイウォール、アプリのダウンロードが必要、低速、絵文字が少ない"
  },
  "scenesTitle": "活用シーン",
  "scenes": [
    {
      "title": "テキストメッセージとリアクション",
      "icon": "💬",
      "desc": "iMessage、WhatsApp、Discordで泣き顔や嬉し泣きをコピー＆ペースト。リアクションやミームに最適です。"
    },
    {
      "title": "ソーシャルメディア",
      "icon": "📱",
      "desc": "Instagramのキャプション、TikTokのコメント、Twitterで泣き顔絵文字のコピー＆ペーストを使用。ワンクリックでコピー＆ペーストできます。"
    },
    {
      "title": "コンテンツとミーム",
      "icon": "😢",
      "desc": "ミームや投稿用に嬉し泣きや泣き顔の絵文字を見つけましょう。キーワードで検索して即座にコピーできます。"
    }
  ],
  "rating": {
    "title": "泣き顔絵文字のコピー＆ペーストで信頼されています",
    "rating": "4.9/5（1万人以上のユーザーから）",
    "text": "「Discordやテキストメッセージで泣き顔や嬉し泣きの絵文字を素早く取得できる方法です。」Toolazeでオンラインで泣き顔絵文字をコピー＆ペースト。無料で登録不要。"
  },
  "faqTitle": "よくある質問",
  "faq": [
    {
      "q": "泣き顔絵文字のコピー＆ペーストは無料ですか？",
      "a": "はい。Toolazeは100%無料です。登録や広告なしで、泣き顔、大泣き、嬉し泣きの絵文字を好きなだけコピー＆ペーストできます。"
    },
    {
      "q": "iPhoneで泣き顔絵文字をコピー＆ペーストできますか？",
      "a": "はい。iPhoneのブラウザでToolazeの絵文字ページを開き、コピーしたい絵文字をタップして、iMessageやアプリに貼り付けてください。"
    },
    {
      "q": "嬉し泣きの絵文字はどこでコピー＆ペーストできますか？",
      "a": "Toolazeで「泣く」または「笑う」と検索すると、嬉し泣きの絵文字が表示されます。クリックしてコピーし、Discord、Instagram、またはメッセージに貼り付けてください。"
    },
    {
      "q": "泣き顔絵文字はDiscordやInstagramで使えますか？",
      "a": "はい。これらは標準のUnicode絵文字であり、Discord、Instagram、TikTok、WhatsAppなどで動作します。必要な場所にコピー＆ペーストするだけです。"
    },
    {
      "q": "Androidで泣き顔絵文字をコピー＆ペーストできますか？",
      "a": "はい。AndroidのブラウザでToolazeを使用して、泣き顔絵文字をコピー＆ペーストしてください。アプリのダウンロードは不要です。"
    }
  ]
}