{
  "in_menu": true,
  "metadata": {
    "title": "免費線上 AI 情侶照片生成器 - 上傳一張照片，挑選場景 | Toolaze",
    "description": "使用 Toolaze 免費線上 AI 情侶照片生成器。上傳一至兩張情侶照片，選擇婚禮、旅遊或攝影棚等預設場景，即可在幾秒鐘內生成寫實的情侶照。"
  },
  "topComponent": "ai-couple-photo-maker",
  "sectionsOrder": [
    "howToUse",
    "features",
    "intro",
    "comparison",
    "scenes",
    "rating",
    "faq"
  ],
  "hero": {
    "h1": "免費線上 <span class=\"text-gradient\">AI 情侶照片生成器</span>",
    "desc": "上傳一至兩張情侶照片，選擇預設的浪漫場景，透過 Toolaze 在幾秒鐘內生成寫實且具電影感的情侶肖像。"
  },
  "howToUse": {
    "title": "如何製作 AI 情侶照",
    "steps": [
      {
        "title": "上傳照片",
        "desc": "上傳一至兩張情侶照片（JPG、PNG 或 WebP 格式）。"
      },
      {
        "title": "選擇範本",
        "desc": "選擇風格或自訂預設場景，如：雨中巴黎、求婚或海灘。"
      },
      {
        "title": "生成與下載",
        "desc": "點擊「生成」來創建您的 1K PNG 情侶照片，並下載最佳結果。"
      }
    ]
  },
  "features": {
    "title": "核心功能",
    "items": [
      {
        "icon": "📷",
        "iconType": "quality",
        "title": "支援一至兩張照片輸入",
        "desc": "可上傳一或兩張參考照片，在每個生成的場景中保持人物身份與情侶間的化學反應。"
      },
      {
        "icon": "🎭",
        "iconType": "multimodal",
        "title": "預設場景範本",
        "desc": "從精心挑選的範本中挑選，包括：雨中巴黎、頂樓夜景、紅地毯、夕陽海灘等。"
      },
      {
        "icon": "🖼️",
        "iconType": "quality",
        "title": "自動比例，1K PNG 輸出",
        "desc": "針對此工作流程優化的輸出設定：自動長寬比、PNG 格式以及 1K 解析度。"
      },
      {
        "icon": "⚡",
        "iconType": "speed",
        "title": "快速生成情侶照",
        "desc": "透過基於瀏覽器的工作流程，快速生成寫實的時尚雜誌風格情侶照。"
      },
      {
        "icon": "🧩",
        "iconType": "quality",
        "title": "風格與自訂範本",
        "desc": "使用現成的風格提示詞或自訂預設（如求婚、海灘、廚房）來進行快速迭代。"
      },
      {
        "icon": "💎",
        "iconType": "free",
        "title": "簡單的點數規則",
        "desc": "每次生成固定使用 40 點，讓使用者獲得可預測且一致的工作流程。"
      }
    ]
  },
  "intro": {
    "title": "為什麼選擇 Toolaze AI 情侶照片生成器？",
    "content": [
      {
        "title": "場景優先的情侶照",
        "text": "大多數圖像工具需要複雜的提示詞才能獲得高品質的浪漫情侶照。Toolaze 簡化了流程，提供場景優先的範本、固定的生成設定以及專為快速成功設計的視覺化過程。"
      },
      {
        "title": "專為真實情侶參考設計",
        "text": "您可以上傳一張合照，或在上傳兩張參考照以獲得更清晰的身份特徵。範本將引導構圖與氛圍，同時保持五官一致性。"
      }
    ]
  },
  "comparison": {
    "title": "Toolaze vs 其他 AI 情侶照生成器",
    "smartChoice": "智慧首選",
    "toolaze": "Toolaze",
    "vs": "VS",
    "otherTools": "其他工具",
    "toolazeFeatures": "支援一/兩張照片上傳, 場景優先預設, 固定優化設定, 一致的浪漫風格流程, 可預測的 40 點數消耗, 快速生成流程",
    "othersFeatures": "需依賴重度提示詞, 缺乏場景引導, 參數預設不一致, 更多試錯成本, 點數預期不明確, 迭代速度較慢"
  },
  "scenesTitle": "應用場景",
  "scenes": [
    {
      "icon": "💍",
      "title": "婚禮與求婚",
      "desc": "為求婚、訂婚公告和婚紗風格的肖像創建浪漫場景。"
    },
    {
      "icon": "🌆",
      "title": "城市約會之夜",
      "desc": "生成頂樓、夜晚街道或紅地毯氛圍，打造高端生活風格的情侶視覺效果。"
    },
    {
      "icon": "🏖️",
      "title": "旅行與假期",
      "desc": "將普通情侶照轉化為夕陽海灘、山脈或充滿度假感的珍貴回憶。"
    }
  ],
  "rating": {
    "title": "AI 情侶照片生成器",
    "rating": "4.9/5 來自 10,000+ 創作者",
    "text": "使用固定的品質設定與精選場景範本創建浪漫情侶照。Toolaze 幫助創作者快速生成精緻的情侶視覺內容。"
  },
  "faqTitle": "常見問題",
  "faq": [
    {
      "q": "AI 情侶照片生成器是如何運作的？",
      "a": "上傳一或兩張情侶照片，選擇場景範本，然後點擊生成。提示詞和設定已針對寫實的雜誌風格輸出進行了優化。"
    },
    {
      "q": "我可以只上傳一張照片嗎？還是需要兩張？",
      "a": "兩者皆支援。您可以根據現有的素材，上傳單張情侶合照或兩張分開的參考照片。"
    },
    {
      "q": "輸出會使用什麼設定？",
      "a": "此頁面使用固定設定：Nano Banana 2 模型、自動長寬比、PNG 格式以及 1K 解析度。"
    },
    {
      "q": "使用者可以在此頁面切換模型嗎？",
      "a": "不可以。模型切換功能已被隱藏，以保持此登錄頁面情侶照工作流程的一致性。"
    },
    {
      "q": "生成一次需要多少點數？",
      "a": "每次生成消耗 40 點。點數規則直接顯示在「生成」按鈕上方。"
    },
    {
      "q": "範本包含預設與自訂選項嗎？",
      "a": "是的。範本區域包含「風格」預設以及「自訂」預設（如求婚、海灘與廚房）。"
    }
  ],
  "moreTools": "更多 AI 工具"
}