{
  "metadata": {
    "title": "貓咪表情符號複製與貼上 - 免費線上工具 | Toolaze",
    "description": "線上免費複製與貼上貓咪表情符號。可愛貓咪、黑貓、星星眼貓咪。一鍵複製貼上到任何應用程式，無需註冊。"
  },
  "sectionsOrder": [
    "howToUse",
    "intro",
    "performanceMetrics",
    "comparison",
    "scenes",
    "rating",
    "faq"
  ],
  "hero": {
    "h1": "貓咪表情符號複製與貼上",
    "desc": "線上免費複製與貼上貓咪表情符號。獲取可愛貓咪、黑貓和星星眼貓咪表情。一鍵複製，適用於 iPhone、Android、Discord、Instagram。"
  },
  "intro": {
    "title": "為什麼要在線上複製與貼上貓咪表情符號？",
    "content": [
      {
        "title": "什麼是貓咪表情符號？",
        "text": "貓咪表情符號 (🐱, 🐈, 😺) 是最受歡迎的表情符號之一，用於表達可愛、有趣或愛貓的氛圍。人們搜尋貓咪表情符號複製與貼上，以便在訊息、個人簡介和社群貼文中使用。透過 Toolaze，您可以在一個地方複製並貼上貓咪表情符號、可愛貓咪表情符號、黑貓表情符號，甚至是星星眼貓咪表情符號，無需應用程式或註冊。瀏覽「動物與自然」或搜尋「cat」即可找到貓咪表情符號。傷心貓咪表情符號和可愛貓咪表情符號只需點擊一下即可複製。使用我們的完整 <a href=\"/zh-TW/emoji-copy-and-paste\" class=\"text-indigo-600 hover:text-purple-600 font-semibold underline decoration-2 underline-offset-2\">表情符號複製與貼上</a> 工具來獲取更多動物和符號。"
      },
      {
        "title": "在任何裝置上複製與貼上貓咪表情符號",
        "text": "無論您是在 Discord、Instagram 還是 iPhone 上需要貓咪表情符號，Toolaze 都能在您的瀏覽器中運行。點擊貓咪、可愛貓咪或黑貓表情符號即可複製，然後貼到任何地方。貓咪表情符號複製貼上是即時的，您的最近使用列表會儲存在本地。透過搜尋可以輕鬆找到星星眼貓咪和傷心貓咪表情符號。所有貓咪表情符號均為標準 Unicode，可在每個平台上正確顯示。"
      }
    ]
  },
  "specs": {
    "engine": "基於瀏覽器的表情符號選擇器 - 用戶端",
    "limit": "無限制表情符號 - 所有標準 Unicode 類別",
    "logic": "搜尋 + 類別瀏覽 + 最近使用",
    "privacy": "100% 用戶端（僅本地儲存最近記錄）"
  },
  "performanceMetrics": {
    "title": "技術規格",
    "metrics": [
      {
        "label": "類別",
        "value": "動物與自然（貓、可愛貓、黑貓、星星眼貓）"
      },
      {
        "label": "搜尋",
        "value": "關鍵字搜尋，例如：cat、cute、black cat、star eyes"
      },
      {
        "label": "複製",
        "value": "一鍵複製到剪貼簿"
      },
      {
        "label": "平台支援",
        "value": "iPhone, Android, Discord, Instagram, TikTok, WhatsApp"
      },
      {
        "label": "隱私",
        "value": "無伺服器上傳；最近列表僅儲存在本地"
      }
    ]
  },
  "howToUse": {
    "title": "如何複製與貼上貓咪表情符號",
    "steps": [
      {
        "title": "打開表情符號選擇器",
        "desc": "前往 Toolaze 表情符號複製與貼上，搜尋「cat」或瀏覽「動物與自然」。"
      },
      {
        "title": "選擇您的貓咪表情符號",
        "desc": "點擊貓咪、可愛貓咪、黑貓或星星眼貓咪表情符號進行複製與貼上。"
      },
      {
        "title": "貼到任何地方",
        "desc": "使用 Ctrl+V（Mac 為 Cmd+V）貼到訊息、個人簡介或社群貼文中。"
      }
    ]
  },
  "comparison": {
    "title": "為什麼選擇 Toolaze？",
    "toolaze": "Toolaze 💎",
    "others": "其他工具",
    "vs": "VS",
    "smartChoice": "明智之選",
    "otherTools": "其他工具",
    "toolazeFeatures": "免費、無需註冊、搜尋 貓/可愛/黑貓、一鍵複製、最近使用、在瀏覽器中運行",
    "othersFeatures": "需要註冊、搜尋功能有限、廣告或付費牆、需下載 App、速度較慢"
  },
  "scenesTitle": "使用場景",
  "scenes": [
    {
      "icon": "🐱",
      "title": "簡訊與通訊",
      "desc": "將貓咪表情符號複製並貼到 iMessage 或 WhatsApp。一鍵複製可愛貓咪表情符號，適用於任何聊天。"
    },
    {
      "icon": "📱",
      "title": "社群媒體與個人簡介",
      "desc": "在 Instagram 個人簡介或 TikTok 中使用貓咪表情符號。黑貓表情符號複製貼上，以及用於貼文和說明文字的貓咪表情符號。"
    },
    {
      "icon": "😺",
      "title": "Discord 與趣味",
      "desc": "獲取星星眼貓咪或傷心貓咪表情符號，用於 Discord 和迷因。立即複製並貼上貓咪表情符號。"
    }
  ],
  "rating": {
    "title": "值得信賴的貓咪表情符號複製與貼上工具",
    "rating": "4.9/5 來自 10,000+ 名使用者",
    "text": "「為 Discord 和 Instagram 複製貼上貓咪表情符號的快捷方式。」使用 Toolaze 複製與貼上貓咪表情符號——免費且無需註冊。"
  },
  "faqTitle": "常見問題",
  "faq": [
    {
      "q": "複製與貼上貓咪表情符號是免費的嗎？",
      "a": "是的。Toolaze 100% 免費。您可以根據需要隨意複製並貼上貓咪表情符號、可愛貓咪表情符號和黑貓表情符號，無需註冊或廣告。"
    },
    {
      "q": "在哪裡可以找到可愛貓咪表情符號複製與貼上？",
      "a": "在 Toolaze 上，搜尋「cat」或「cute」即可找到可愛貓咪表情符號。點擊即可將貓咪表情符號複製並貼到訊息或社群媒體中。"
    },
    {
      "q": "我可以複製並貼上黑貓表情符號嗎？",
      "a": "是的。搜尋「black cat」或瀏覽「動物與自然」。黑貓表情符號複製與貼上適用於所有裝置和應用程式。"
    },
    {
      "q": "如何獲取星星眼貓咪表情符號複製與貼上？",
      "a": "在 Toolaze 上，搜尋「cat」或「star eyes」即可找到星星眼貓咪表情符號。點擊即可複製並貼上。"
    },
    {
      "q": "貓咪表情符號在 Discord 和 Instagram 上可以使用嗎？",
      "a": "是的。它們是標準 Unicode。將貓咪表情符號複製並貼到 Discord、Instagram、TikTok、WhatsApp 或任何支援表情符號的應用程式中。"
    }
  ]
}